trulens/_bundle/__init__.py
trulens/_bundle/py.typed
trulens-2.5.0.dist-info/LICENSE
trulens-2.5.0.dist-info/METADATA
trulens-2.5.0.dist-info/WHEEL
trulens-2.5.0.dist-info/RECORD
